{
  "issue": "MOM-303",
  "generated_at": "2026-04-26T20:14:31.870Z",
  "sample_size": 50,
  "method": "deterministic_random_hash_selection",
  "source": "LOW confidence tier from full report",
  "checks": [
    {
      "id": "_duUqfwuAaVNuIubWDctImAAPed7ORWDyM4h3WlA",
      "sku": "default",
      "category": "louis vuitton / 女包",
      "brand": "Unknown",
      "original_title": "LV",
      "cleaned_title": "LV",
      "changed": false,
      "method": "gentle_original_fallback",
      "confidence": "low",
      "confidence_level": "LOW",
      "uncertainty_reason": "no_known_model_pattern",
      "deterministic": true
    },
    {
      "id": "_dvQqfkCO39qIvsfhMSEigke8zvFg-5qQSvhCSIg",
      "sku": "default",
      "category": "yves saint laurent / 女包",
      "brand": "Unknown",
      "original_title": "YSL",
      "cleaned_title": "YSL",
      "changed": false,
      "method": "gentle_original_fallback",
      "confidence": "low",
      "confidence_level": "LOW",
      "uncertainty_reason": "no_known_model_pattern",
      "deterministic": true
    },
    {
      "id": "_diKqft5czxSd9Y9J9OwwFNhHSoh8MH0-0Bo-KaA",
      "sku": "default",
      "category": "uncategorized",
      "brand": "Unknown",
      "original_title": "Loro piana",
      "cleaned_title": "Loro piana",
      "changed": false,
      "method": "gentle_original_fallback",
      "confidence": "low",
      "confidence_level": "LOW",
      "uncertainty_reason": "no_known_model_pattern",
      "deterministic": true
    },
    {
      "id": "_dsMqfzjfa26p8ViVBOkBlA5Qk6EKaZRubIWMfSg",
      "sku": "default",
      "category": "goose / 大鹅 衣",
      "brand": "Unknown",
      "original_title": "CANADA GOOSE",
      "cleaned_title": "CANADA GOOSE",
      "changed": false,
      "method": "gentle_original_fallback",
      "confidence": "low",
      "confidence_level": "LOW",
      "uncertainty_reason": "no_known_model_pattern",
      "deterministic": true
    },
    {
      "id": "_dgOqf66BzPKOBJGiXix4_JLvwsxklvJ6vwmbiKA",
      "sku": "default",
      "category": "goose / 大鹅 衣",
      "brand": "Unknown",
      "original_title": "CANADA GOOSE",
      "cleaned_title": "CANADA GOOSE",
      "changed": false,
      "method": "gentle_original_fallback",
      "confidence": "low",
      "confidence_level": "LOW",
      "uncertainty_reason": "no_known_model_pattern",
      "deterministic": true
    },
    {
      "id": "_dj8qflolacUo6C9dA2lMxWL0RTR5DEsbzBXMPYg",
      "sku": "default",
      "category": "louis vuitton / 女包",
      "brand": "Unknown",
      "original_title": "LV",
      "cleaned_title": "LV",
      "changed": false,
      "method": "gentle_original_fallback",
      "confidence": "low",
      "confidence_level": "LOW",
      "uncertainty_reason": "no_known_model_pattern",
      "deterministic": true
    },
    {
      "id": "_duGqf5HFLsxXQ7W6WeMDHQfUl4vQ-MmmCr4-R2g",
      "sku": "default",
      "category": "chanel / 女包",
      "brand": "Unknown",
      "original_title": "Chanel",
      "cleaned_title": "Chanel",
      "changed": false,
      "method": "gentle_original_fallback",
      "confidence": "low",
      "confidence_level": "LOW",
      "uncertainty_reason": "no_known_model_pattern",
      "deterministic": true
    },
    {
      "id": "_dgSqfjMRq3qp6kAWsYzMvGbgjP5264mdIzrlN-g",
      "sku": "default",
      "category": "uncategorized",
      "brand": "Unknown",
      "original_title": "Louis Vuitton",
      "cleaned_title": "Louis Vuitton",
      "changed": false,
      "method": "gentle_original_fallback",
      "confidence": "low",
      "confidence_level": "LOW",
      "uncertainty_reason": "no_known_model_pattern",
      "deterministic": true
    },
    {
      "id": "_d_qqfooqOIoTA_1Zqp1q86YaJ57Ajwka_d8gMPA",
      "sku": "default",
      "category": "uncategorized",
      "brand": "Unknown",
      "original_title": "LV",
      "cleaned_title": "LV",
      "changed": false,
      "method": "gentle_original_fallback",
      "confidence": "low",
      "confidence_level": "LOW",
      "uncertainty_reason": "no_known_model_pattern",
      "deterministic": true
    },
    {
      "id": "_dl6qfvUZUzmt-5Dk1yAEYWv1j100aKMJJfyFhKA",
      "sku": "default",
      "category": "uncategorized",
      "brand": "Unknown",
      "original_title": "Chanel",
      "cleaned_title": "Chanel",
      "changed": false,
      "method": "gentle_original_fallback",
      "confidence": "low",
      "confidence_level": "LOW",
      "uncertainty_reason": "no_known_model_pattern",
      "deterministic": true
    },
    {
      "id": "_dgGqf3o7ELeWlw5T527JmbkMMY6CifmTkF8PXRg",
      "sku": "default",
      "category": "chanel / 女包",
      "brand": "Unknown",
      "original_title": "Chanel",
      "cleaned_title": "Chanel",
      "changed": false,
      "method": "gentle_original_fallback",
      "confidence": "low",
      "confidence_level": "LOW",
      "uncertainty_reason": "no_known_model_pattern",
      "deterministic": true
    },
    {
      "id": "_dseqfM73pRYORIDpAfgMCe1i6-0vpfo-SfdEyHA",
      "sku": "default",
      "category": "goose / 大鹅 衣",
      "brand": "Unknown",
      "original_title": "CANADA GOOSE",
      "cleaned_title": "CANADA GOOSE",
      "changed": false,
      "method": "gentle_original_fallback",
      "confidence": "low",
      "confidence_level": "LOW",
      "uncertainty_reason": "no_known_model_pattern",
      "deterministic": true
    },
    {
      "id": "_djGqf-jpWAk4gBYBQvDx1ZQv5UQ01QDX14VXzwg",
      "sku": "default",
      "category": "uncategorized",
      "brand": "Unknown",
      "original_title": "LV",
      "cleaned_title": "LV",
      "changed": false,
      "method": "gentle_original_fallback",
      "confidence": "low",
      "confidence_level": "LOW",
      "uncertainty_reason": "no_known_model_pattern",
      "deterministic": true
    },
    {
      "id": "_dscqf5KwT7hhVhCsN5_Mx1bzHPWSsiGtgS2O37g",
      "sku": "default",
      "category": "goose / 大鹅 衣",
      "brand": "Unknown",
      "original_title": "CANADA GOOSE",
      "cleaned_title": "CANADA GOOSE",
      "changed": false,
      "method": "gentle_original_fallback",
      "confidence": "low",
      "confidence_level": "LOW",
      "uncertainty_reason": "no_known_model_pattern",
      "deterministic": true
    },
    {
      "id": "_dFMqfCiyz0d-mp_qXKjhDXimTWFcfxckglkupew",
      "sku": "default",
      "category": "louis vuitton / 女包",
      "brand": "Unknown",
      "original_title": "LV",
      "cleaned_title": "LV",
      "changed": false,
      "method": "gentle_original_fallback",
      "confidence": "low",
      "confidence_level": "LOW",
      "uncertainty_reason": "no_known_model_pattern",
      "deterministic": true
    },
    {
      "id": "_do_qfvJIEE7ymYDhJxJ_8LUzRoym4qZIGdrOYJw",
      "sku": "default",
      "category": "uncategorized",
      "brand": "Unknown",
      "original_title": "Louis Vuitton",
      "cleaned_title": "Louis Vuitton",
      "changed": false,
      "method": "gentle_original_fallback",
      "confidence": "low",
      "confidence_level": "LOW",
      "uncertainty_reason": "no_known_model_pattern",
      "deterministic": true
    },
    {
      "id": "_dueqfkOG8jB4qQOFxlu34cEfPjIElKzT6Hb0mlQ",
      "sku": "default",
      "category": "louis vuitton / 女包",
      "brand": "Unknown",
      "original_title": "LV",
      "cleaned_title": "LV",
      "changed": false,
      "method": "gentle_original_fallback",
      "confidence": "low",
      "confidence_level": "LOW",
      "uncertainty_reason": "no_known_model_pattern",
      "deterministic": true
    },
    {
      "id": "_dqtqfOTDe2yzwDMdyN18IxeoG4u4X7RXYwBhPqA",
      "sku": "default",
      "category": "chanel / 女包",
      "brand": "Unknown",
      "original_title": "Chanel",
      "cleaned_title": "Chanel",
      "changed": false,
      "method": "gentle_original_fallback",
      "confidence": "low",
      "confidence_level": "LOW",
      "uncertainty_reason": "no_known_model_pattern",
      "deterministic": true
    },
    {
      "id": "_doLqflCdpX7faYmx2_1QK5EBAYQuAcdPBx6IrGg",
      "sku": "default",
      "category": "yves saint laurent / 女包",
      "brand": "Unknown",
      "original_title": "YSL",
      "cleaned_title": "YSL",
      "changed": false,
      "method": "gentle_original_fallback",
      "confidence": "low",
      "confidence_level": "LOW",
      "uncertainty_reason": "no_known_model_pattern",
      "deterministic": true
    },
    {
      "id": "_dxmqfEI-BDIphU3QtdOU8Dcm95FPkLltBziBB3w",
      "sku": "default",
      "category": "uncategorized",
      "brand": "Unknown",
      "original_title": "Chanel",
      "cleaned_title": "Chanel",
      "changed": false,
      "method": "gentle_original_fallback",
      "confidence": "low",
      "confidence_level": "LOW",
      "uncertainty_reason": "no_known_model_pattern",
      "deterministic": true
    },
    {
      "id": "_drMqfoCXjdfPDxyl_jmxasfLBC41H-Lnxr63kdw",
      "sku": "default",
      "category": "louis vuitton / 女包",
      "brand": "Unknown",
      "original_title": "LV",
      "cleaned_title": "LV",
      "changed": false,
      "method": "gentle_original_fallback",
      "confidence": "low",
      "confidence_level": "LOW",
      "uncertainty_reason": "no_known_model_pattern",
      "deterministic": true
    },
    {
      "id": "_dgpqfkk38BjYgf36kN87ZYKpvDLkbvTc2_2xMHg",
      "sku": "default",
      "category": "uncategorized",
      "brand": "Unknown",
      "original_title": "LV",
      "cleaned_title": "LV",
      "changed": false,
      "method": "gentle_original_fallback",
      "confidence": "low",
      "confidence_level": "LOW",
      "uncertainty_reason": "no_known_model_pattern",
      "deterministic": true
    },
    {
      "id": "_dkFqf08O5GSBHPM_dDbsJD6dmJaVSX6ZSjOXMHQ",
      "sku": "default",
      "category": "uncategorized",
      "brand": "Unknown",
      "original_title": "Louis Vuitton",
      "cleaned_title": "Louis Vuitton",
      "changed": false,
      "method": "gentle_original_fallback",
      "confidence": "low",
      "confidence_level": "LOW",
      "uncertainty_reason": "no_known_model_pattern",
      "deterministic": true
    },
    {
      "id": "_dm9qfWOUNwnuO_ThIEu3mRtrAHA5-_0So08DLXA",
      "sku": "default",
      "category": "goose / 大鹅 衣",
      "brand": "Unknown",
      "original_title": "CANADA GOOSE",
      "cleaned_title": "CANADA GOOSE",
      "changed": false,
      "method": "gentle_original_fallback",
      "confidence": "low",
      "confidence_level": "LOW",
      "uncertainty_reason": "no_known_model_pattern",
      "deterministic": true
    },
    {
      "id": "_dr_qfCPVDfFTi6pxY5cdmoijt6bGfgXgznT0lMw",
      "sku": "default",
      "category": "gucci / 女包",
      "brand": "Unknown",
      "original_title": "Gucci",
      "cleaned_title": "Gucci",
      "changed": false,
      "method": "gentle_original_fallback",
      "confidence": "low",
      "confidence_level": "LOW",
      "uncertainty_reason": "no_known_model_pattern",
      "deterministic": true
    },
    {
      "id": "_ddPqfxuEphMdTAfYH7T-0z2NekrW3suDAEmPdsw",
      "sku": "default",
      "category": "uncategorized",
      "brand": "Unknown",
      "original_title": "LV",
      "cleaned_title": "LV",
      "changed": false,
      "method": "gentle_original_fallback",
      "confidence": "low",
      "confidence_level": "LOW",
      "uncertainty_reason": "no_known_model_pattern",
      "deterministic": true
    },
    {
      "id": "_dmhqf8jYAa0wgz1T_LXae7he9WN3RgxVEZWsAyA",
      "sku": "default",
      "category": "louis vuitton / 女包",
      "brand": "Unknown",
      "original_title": "Louis Vuitton",
      "cleaned_title": "Louis Vuitton",
      "changed": false,
      "method": "gentle_original_fallback",
      "confidence": "low",
      "confidence_level": "LOW",
      "uncertainty_reason": "no_known_model_pattern",
      "deterministic": true
    },
    {
      "id": "_dW3qfMB8IEXaoolpXENBycQviuQDgZz4vTHh9Rg",
      "sku": "default",
      "category": "goose / 大鹅 衣",
      "brand": "Unknown",
      "original_title": "CANADA GOOSE",
      "cleaned_title": "CANADA GOOSE",
      "changed": false,
      "method": "gentle_original_fallback",
      "confidence": "low",
      "confidence_level": "LOW",
      "uncertainty_reason": "no_known_model_pattern",
      "deterministic": true
    },
    {
      "id": "_deCqfJvfNKgtNyZVBcN8h-pBTsz5EaizizyDogA",
      "sku": "default",
      "category": "goose / 大鹅 衣",
      "brand": "Unknown",
      "original_title": "CANADA GOOSE",
      "cleaned_title": "CANADA GOOSE",
      "changed": false,
      "method": "gentle_original_fallback",
      "confidence": "low",
      "confidence_level": "LOW",
      "uncertainty_reason": "no_known_model_pattern",
      "deterministic": true
    },
    {
      "id": "_dPYqf1WJ3HcifALoSC2JksXVYXK2o8P5YCNDVXQ",
      "sku": "default",
      "category": "louis vuitton / 女包",
      "brand": "Unknown",
      "original_title": "Louis Vuitton",
      "cleaned_title": "Louis Vuitton",
      "changed": false,
      "method": "gentle_original_fallback",
      "confidence": "low",
      "confidence_level": "LOW",
      "uncertainty_reason": "no_known_model_pattern",
      "deterministic": true
    },
    {
      "id": "_dHzqf65knDYLel2V4WY_VvK3vSfQ8vjVWoSvpxA",
      "sku": "default",
      "category": "prada /女包",
      "brand": "Unknown",
      "original_title": "Prada",
      "cleaned_title": "Prada",
      "changed": false,
      "method": "gentle_original_fallback",
      "confidence": "low",
      "confidence_level": "LOW",
      "uncertainty_reason": "no_known_model_pattern",
      "deterministic": true
    },
    {
      "id": "_d-zqfD3K0C0uSE3__fTEF9d46HtBy2EWPU2bZUw",
      "sku": "default",
      "category": "goose / 大鹅 衣",
      "brand": "Unknown",
      "original_title": "CANADA GOOSE",
      "cleaned_title": "CANADA GOOSE",
      "changed": false,
      "method": "gentle_original_fallback",
      "confidence": "low",
      "confidence_level": "LOW",
      "uncertainty_reason": "no_known_model_pattern",
      "deterministic": true
    },
    {
      "id": "_dX-qfTdruuek5Td_0zqJ26hYWYbiScqIYx3JpMQ",
      "sku": "default",
      "category": "uncategorized",
      "brand": "Unknown",
      "original_title": "chanel",
      "cleaned_title": "chanel",
      "changed": false,
      "method": "gentle_original_fallback",
      "confidence": "low",
      "confidence_level": "LOW",
      "uncertainty_reason": "no_known_model_pattern",
      "deterministic": true
    },
    {
      "id": "_dh0qfOEIHa_TM_bPV_3TcL3ejO0x4gpHc3SyDXA",
      "sku": "default",
      "category": "goose / 大鹅 衣",
      "brand": "Unknown",
      "original_title": "CANADA GOOSE",
      "cleaned_title": "CANADA GOOSE",
      "changed": false,
      "method": "gentle_original_fallback",
      "confidence": "low",
      "confidence_level": "LOW",
      "uncertainty_reason": "no_known_model_pattern",
      "deterministic": true
    },
    {
      "id": "_dcnqfxAe5pdeHpQruYmun7_ozt-c3Z-xOPDqH4w",
      "sku": "default",
      "category": "goose / 大鹅 衣",
      "brand": "Unknown",
      "original_title": "CANADA GOOSE",
      "cleaned_title": "CANADA GOOSE",
      "changed": false,
      "method": "gentle_original_fallback",
      "confidence": "low",
      "confidence_level": "LOW",
      "uncertainty_reason": "no_known_model_pattern",
      "deterministic": true
    },
    {
      "id": "_dkZqfsR5j2FybwMMao61G-T8T3dfsP86HoZMpJA",
      "sku": "default",
      "category": "uncategorized",
      "brand": "Unknown",
      "original_title": "LV",
      "cleaned_title": "LV",
      "changed": false,
      "method": "gentle_original_fallback",
      "confidence": "low",
      "confidence_level": "LOW",
      "uncertainty_reason": "no_known_model_pattern",
      "deterministic": true
    },
    {
      "id": "_dq6qffDoCyPoHZvDxzWxTnuOcsH_scYMt92eHUw",
      "sku": "default",
      "category": "miumiu/女包",
      "brand": "Unknown",
      "original_title": "MiuMiu",
      "cleaned_title": "MiuMiu",
      "changed": false,
      "method": "gentle_original_fallback",
      "confidence": "low",
      "confidence_level": "LOW",
      "uncertainty_reason": "no_known_model_pattern",
      "deterministic": true
    },
    {
      "id": "_dP6qfrCW2Qbiq0mPkSYRFT3tCULgkL3EnX3Snkw",
      "sku": "default",
      "category": "goose / 大鹅 衣",
      "brand": "Unknown",
      "original_title": "CANADA GOOSE",
      "cleaned_title": "CANADA GOOSE",
      "changed": false,
      "method": "gentle_original_fallback",
      "confidence": "low",
      "confidence_level": "LOW",
      "uncertainty_reason": "no_known_model_pattern",
      "deterministic": true
    },
    {
      "id": "_diMqfTvqQS9JVgbezCLbgh-4xGZO4jTuqVKjW6A",
      "sku": "default",
      "category": "goose / 大鹅 衣",
      "brand": "Unknown",
      "original_title": "CANADA GOOSE",
      "cleaned_title": "CANADA GOOSE",
      "changed": false,
      "method": "gentle_original_fallback",
      "confidence": "low",
      "confidence_level": "LOW",
      "uncertainty_reason": "no_known_model_pattern",
      "deterministic": true
    },
    {
      "id": "_daRqfPDcn1uDG9PpoSB4qF6Z8G4dn29D1hRAlgw",
      "sku": "default",
      "category": "goose / 大鹅 衣",
      "brand": "Unknown",
      "original_title": "CANADA GOOSE",
      "cleaned_title": "CANADA GOOSE",
      "changed": false,
      "method": "gentle_original_fallback",
      "confidence": "low",
      "confidence_level": "LOW",
      "uncertainty_reason": "no_known_model_pattern",
      "deterministic": true
    },
    {
      "id": "_dt6qfUyZqT5kuHB-gOZ7CyVvFUa-IHJ8av6f8FA",
      "sku": "default",
      "category": "goose / 大鹅 衣",
      "brand": "Unknown",
      "original_title": "CANADA GOOSE",
      "cleaned_title": "CANADA GOOSE",
      "changed": false,
      "method": "gentle_original_fallback",
      "confidence": "low",
      "confidence_level": "LOW",
      "uncertainty_reason": "no_known_model_pattern",
      "deterministic": true
    },
    {
      "id": "_dFRqfjloCKvnWxKLtlFilMk4_TdRLAg0oFJqsuA",
      "sku": "default",
      "category": "uncategorized",
      "brand": "Unknown",
      "original_title": "LV",
      "cleaned_title": "LV",
      "changed": false,
      "method": "gentle_original_fallback",
      "confidence": "low",
      "confidence_level": "LOW",
      "uncertainty_reason": "no_known_model_pattern",
      "deterministic": true
    },
    {
      "id": "_dE2qf2RJ50nU8fnTm9pZO_GYbbxSoJmjISTJZ-w",
      "sku": "default",
      "category": "chanel / 女包",
      "brand": "Unknown",
      "original_title": "Chanel",
      "cleaned_title": "Chanel",
      "changed": false,
      "method": "gentle_original_fallback",
      "confidence": "low",
      "confidence_level": "LOW",
      "uncertainty_reason": "no_known_model_pattern",
      "deterministic": true
    },
    {
      "id": "_dmVqfjoNSyi6X0BxHsBOB84-ifIwOQGmdwrukCA",
      "sku": "default",
      "category": "louis vuitton / 女包",
      "brand": "Unknown",
      "original_title": "LV",
      "cleaned_title": "LV",
      "changed": false,
      "method": "gentle_original_fallback",
      "confidence": "low",
      "confidence_level": "LOW",
      "uncertainty_reason": "no_known_model_pattern",
      "deterministic": true
    },
    {
      "id": "_dkzqf2Wt3BieITvEfICTTASIKJqwkbVyRaGqNVg",
      "sku": "default",
      "category": "prada /女包",
      "brand": "Unknown",
      "original_title": "Prada",
      "cleaned_title": "Prada",
      "changed": false,
      "method": "gentle_original_fallback",
      "confidence": "low",
      "confidence_level": "LOW",
      "uncertainty_reason": "no_known_model_pattern",
      "deterministic": true
    },
    {
      "id": "_dxfqf55uuSwF3sTlGd3Lq-EidEtyShcQ7VbOjtw",
      "sku": "default",
      "category": "goose / 大鹅 衣",
      "brand": "Unknown",
      "original_title": "CANADA GOOSE",
      "cleaned_title": "CANADA GOOSE",
      "changed": false,
      "method": "gentle_original_fallback",
      "confidence": "low",
      "confidence_level": "LOW",
      "uncertainty_reason": "no_known_model_pattern",
      "deterministic": true
    },
    {
      "id": "_djvqfKOoK5ekh7ZmIrfHXbfObTfasD9RWlCCBzA",
      "sku": "default",
      "category": "uncategorized",
      "brand": "Unknown",
      "original_title": "LV",
      "cleaned_title": "LV",
      "changed": false,
      "method": "gentle_original_fallback",
      "confidence": "low",
      "confidence_level": "LOW",
      "uncertainty_reason": "no_known_model_pattern",
      "deterministic": true
    },
    {
      "id": "_d-Uqf0wd_znZ8Im6QoCYNBMlmwrIAOJzf7XOt_A",
      "sku": "default",
      "category": "uncategorized",
      "brand": "Unknown",
      "original_title": "LV",
      "cleaned_title": "LV",
      "changed": false,
      "method": "gentle_original_fallback",
      "confidence": "low",
      "confidence_level": "LOW",
      "uncertainty_reason": "no_known_model_pattern",
      "deterministic": true
    },
    {
      "id": "_d83qfpT72p9_Np0FTms3jDuxfsCRKumkgiAHBjA",
      "sku": "default",
      "category": "goose / 大鹅 衣",
      "brand": "Unknown",
      "original_title": "CANADA GOOSE",
      "cleaned_title": "CANADA GOOSE",
      "changed": false,
      "method": "gentle_original_fallback",
      "confidence": "low",
      "confidence_level": "LOW",
      "uncertainty_reason": "no_known_model_pattern",
      "deterministic": true
    },
    {
      "id": "_d6LqfR5n_tYLBfr1f9HwEebR6ri7JjM3s4faA_w",
      "sku": "default",
      "category": "uncategorized",
      "brand": "Unknown",
      "original_title": "LV",
      "cleaned_title": "LV",
      "changed": false,
      "method": "gentle_original_fallback",
      "confidence": "low",
      "confidence_level": "LOW",
      "uncertainty_reason": "no_known_model_pattern",
      "deterministic": true
    }
  ]
}
